{"learner":{"attributes":{"best_iteration":"0","best_score":"1.0"},"feature_names":["dns__query_count","dns__query_rate_per_minute","dns__avg_query_length","dns__max_query_length","dns__avg_entropy","dns__max_entropy","dns__avg_subdomain_depth","dns__max_label_length","dns__avg_label_length","dns__label_entropy_max","dns__unique_subdomain_ratio","dns__base64_pattern_count","dns__hex_pattern_count","dns__numeric_ratio","dns__subdomain_has_numbers_ratio","dns__unique_base_domains","dns__top_domain_query_ratio","dns__max_unique_subdomains_per_domain","dns__txt_record_ratio","dns__null_record_ratio","dns__mx_record_ratio","dns__cname_record_ratio","dns__any_record_ratio","dns__tunneling_type_ratio","dns__record_type_count","dns__avg_response_size","dns__max_response_size","dns__response_variance","dns__nxdomain_ratio","dns__fast_flux_ratio","dns__min_ttl","dns__ttl_variance","dns__inter_query_interval_mean","dns__inter_query_interval_cv","dns__unique_process_count","dns__non_browser_dns_ratio","dns__non_standard_dns_ratio","dns__nx_subdomains_per_top_domain","dns__nx_top_domain_query_ratio","dns__consonant_run_max","dns__digit_letter_run_max","dns__vowel_ratio_min","auth__total_auth_events","auth__successful_logon_count","auth__failed_logon_count","auth__failed_logon_ratio","auth__network_logon_count","auth__interactive_logon_count","auth__remote_interactive_logon_count","auth__service_logon_count","auth__cleartext_logon_count","auth__network_logon_ratio","auth__explicit_credential_count","auth__ntlm_count","auth__kerberos_tgt_count","auth__kerberos_tgs_count","auth__special_logon_count","auth__unique_privileged_users","auth__unique_users","auth__unique_target_hosts","auth__unique_source_ips","auth__lateral_velocity_per_min","auth__max_hosts_per_user","auth__max_failures_per_user","auth__unique_failed_users","auth__max_users_per_source","auth__account_created_count","auth__account_enabled_count","auth__password_reset_count","auth__account_disabled_count","auth__account_deleted_count","auth__account_changed_count","auth__success_after_failures","auth__time_to_first_success_secs","auth__offhours_logon_count","auth__offhours_interactive_count","auth__psexec_invocations","auth__wmic_invocations","auth__winrm_invocations","auth__schtasks_invocations","auth__powershell_encoded_count","auth__lsass_access_count","process__total_process_events","process__credential_tool_count","process__lsass_access_count","process__image_load_count","process__remote_thread_count","process__process_tamper_count","process__psexec_count","process__wmic_count","process__mshta_count","process__rundll32_count","process__regsvr32_count","process__certutil_count","process__bitsadmin_count","process__schtasks_count","process__esentutl_count","process__total_lolbin_count","process__powershell_count","process__encoded_command_count","process__download_command_count","process__amsi_bypass_count","process__office_to_shell_count","process__browser_to_shell_count","process__pipe_event_count","process__pipe_attack_count","process__archive_drop_count","process__user_exe_drop_count","process__file_create_count","process__unique_image_count","process__unique_parent_count","network__total_connections","network__connections_per_minute","network__total_lateral_count","network__smb_count","network__rdp_count","network__winrm_count","network__wmi_count","network__ssh_count","network__netbios_count","network__telnet_count","network__unique_dest_ips","network__unique_dest_ports","network__unique_source_processes","network__internal_connection_count","network__external_connection_count","network__internal_to_external_ratio","network__shell_initiated_count","network__lolbin_initiated_count","network__shell_lateral_count","network__total_bytes_sent","network__total_bytes_received","network__max_bytes_per_connection","temporal__total_event_count","temporal__window_duration_seconds","temporal__events_per_minute","temporal__burst_factor","temporal__per_minute_stdev","temporal__active_minute_count","temporal__off_hours_ratio","temporal__night_hours_ratio","temporal__weekend_ratio","temporal__inter_event_interval_mean","temporal__inter_event_interval_cv","temporal__inter_event_interval_min","temporal__inter_event_interval_max","behavioral__pth_chain_count","behavioral__bruteforce_success_count","behavioral__auth_then_network_count","behavioral__auth_then_process_count","behavioral__priv_escalation_chain","behavioral__unique_users_overall","behavioral__unique_hosts_overall","behavioral__unique_processes_overall","behavioral__host_user_pair_count","behavioral__entity_diversity_score"],"feature_types":[],"gradient_booster":{"model":{"cats":{"enc":[],"feature_segments":[],"sorted_idx":[]},"gbtree_model_param":{"num_parallel_tree":"1","num_trees":"21"},"iteration_indptr":[0,1,2,3,4,5,6,7,8,9,10,11,12,13,14,15,16,17,18,19,20,21],"tree_info":[0,0,0,0,0,0,0,0,0,0,0,0,0,0,0,0,0,0,0,0,0],"trees":[{"base_weights":[-1.0021594E-1,-1.9860628E-1,1.9845979E-1],"categories":[],"categories_nodes":[],"categories_segments":[],"categories_sizes":[],"default_left":[0,0,0],"id":0,"left_children":[1,-1,-1],"loss_changes":[1.0747351E3,0E0,0E0],"parents":[2147483647,0,0],"right_children":[2,-1,-1],"split_conditions":[6E0,-1.9860628E-1,1.9845979E-1],"split_indices":[153,0,0],"split_type":[0,0,0],"sum_hessian":[2.7135294E2,1.425E2,1.2885295E2],"tree_param":{"num_deleted":"0","num_feature":"156","num_nodes":"3","size_leaf_vector":"1"}},{"base_weights":[-4.1336678E-2,-1.8073069E-1,1.8068433E-1],"categories":[],"categories_nodes":[],"categories_segments":[],"categories_sizes":[],"default_left":[0,0,0],"id":1,"left_children":[1,-1,-1],"loss_changes":[9.2443054E2,0E0,0E0],"parents":[2147483647,0,0],"right_children":[2,-1,-1],"split_conditions":[6E0,-1.8073069E-1,1.8068433E-1],"split_indices":[153,0,0],"split_type":[0,0,0],"sum_hessian":[2.812343E2,1.4382703E2,1.3740727E2],"tree_param":{"num_deleted":"0","num_feature":"156","num_nodes":"3","size_leaf_vector":"1"}},{"base_weights":[3.8646776E-2,-1.672111E-1,1.6727866E-1],"categories":[],"categories_nodes":[],"categories_segments":[],"categories_sizes":[],"default_left":[0,0,0],"id":2,"left_children":[1,-1,-1],"loss_changes":[7.896811E2,0E0,0E0],"parents":[2147483647,0,0],"right_children":[2,-1,-1],"split_conditions":[6E0,-1.672111E-1,1.6727866E-1],"split_indices":[153,0,0],"split_type":[0,0,0],"sum_hessian":[2.8047058E2,1.3701172E2,1.4345886E2],"tree_param":{"num_deleted":"0","num_feature":"156","num_nodes":"3","size_leaf_vector":"1"}},{"base_weights":[1.1936754E-1,-1.5672885E-1,1.5689933E-1],"categories":[],"categories_nodes":[],"categories_segments":[],"categories_sizes":[],"default_left":[0,0,0],"id":3,"left_children":[1,-1,-1],"loss_changes":[7.163544E2,0E0,0E0],"parents":[2147483647,0,0],"right_children":[2,-1,-1],"split_conditions":[6E0,-1.5672885E-1,1.5689933E-1],"split_indices":[153,0,0],"split_type":[0,0,0],"sum_hessian":[2.9097934E2,1.3445651E2,1.5652284E2],"tree_param":{"num_deleted":"0","num_feature":"156","num_nodes":"3","size_leaf_vector":"1"}},{"base_weights":[-1.7180007E-2,-1.4831702E-1,1.4828752E-1],"categories":[],"categories_nodes":[],"categories_segments":[],"categories_sizes":[],"default_left":[0,0,0],"id":4,"left_children":[1,-1,-1],"loss_changes":[5.513498E2,0E0,0E0],"parents":[2147483647,0,0],"right_children":[2,-1,-1],"split_conditions":[6E0,-1.4831702E-1,1.4828752E-1],"split_indices":[153,0,0],"split_type":[0,0,0],"sum_hessian":[2.4871983E2,1.2579388E2,1.2292595E2],"tree_param":{"num_deleted":"0","num_feature":"156","num_nodes":"3","size_leaf_vector":"1"}},{"base_weights":[1.7780999E-2,-1.415096E-1,1.4153747E-1],"categories":[],"categories_nodes":[],"categories_segments":[],"categories_sizes":[],"default_left":[0,0,0],"id":5,"left_children":[1,-1,-1],"loss_changes":[4.971667E2,0E0,0E0],"parents":[2147483647,0,0],"right_children":[2,-1,-1],"split_conditions":[6E0,-1.415096E-1,1.4153747E-1],"split_indices":[153,0,0],"split_type":[0,0,0],"sum_hessian":[2.4626294E2,1.2159039E2,1.24672554E2],"tree_param":{"num_deleted":"0","num_feature":"156","num_nodes":"3","size_leaf_vector":"1"}},{"base_weights":[-2.646417E-2,-1.3584885E-1,1.3580047E-1],"categories":[],"categories_nodes":[],"categories_segments":[],"categories_sizes":[],"default_left":[0,0,0],"id":6,"left_children":[1,-1,-1],"loss_changes":[4.1545444E2,0E0,0E0],"parents":[2147483647,0,0],"right_children":[2,-1,-1],"split_conditions":[6E0,-1.3584885E-1,1.3580047E-1],"split_indices":[153,0,0],"split_type":[0,0,0],"sum_hessian":[2.2328247E2,1.1380614E2,1.0947633E2],"tree_param":{"num_deleted":"0","num_feature":"156","num_nodes":"3","size_leaf_vector":"1"}},{"base_weights":[5.3328484E-2,-1.3112329E-1,1.3121706E-1],"categories":[],"categories_nodes":[],"categories_segments":[],"categories_sizes":[],"default_left":[0,0,0],"id":7,"left_children":[1,-1,-1],"loss_changes":[3.9019046E2,0E0,0E0],"parents":[2147483647,0,0],"right_children":[2,-1,-1],"split_conditions":[6E0,-1.3112329E-1,1.3121706E-1],"split_indices":[153,0,0],"split_type":[0,0,0],"sum_hessian":[2.2514816E2,1.0801755E2,1.17130615E2],"tree_param":{"num_deleted":"0","num_feature":"156","num_nodes":"3","size_leaf_vector":"1"}},{"base_weights":[5.9336666E-2,-1.2708595E-1,1.2719582E-1],"categories":[],"categories_nodes":[],"categories_segments":[],"categories_sizes":[],"default_left":[0,0,0],"id":8,"left_children":[1,-1,-1],"loss_changes":[3.3984442E2,0E0,0E0],"parents":[2147483647,0,0],"right_children":[2,-1,-1],"split_conditions":[6E0,-1.2708595E-1,1.2719582E-1],"split_indices":[153,0,0],"split_type":[0,0,0],"sum_hessian":[2.0868555E2,9.9495285E1,1.0919027E2],"tree_param":{"num_deleted":"0","num_feature":"156","num_nodes":"3","size_leaf_vector":"1"}},{"base_weights":[6.524912E-2,-1.2362447E-1,1.237533E-1],"categories":[],"categories_nodes":[],"categories_segments":[],"categories_sizes":[],"default_left":[0,0,0],"id":9,"left_children":[1,-1,-1],"loss_changes":[2.97129E2,0E0,0E0],"parents":[2147483647,0,0],"right_children":[2,-1,-1],"split_conditions":[6E0,-1.2362447E-1,1.237533E-1],"split_indices":[153,0,0],"split_type":[0,0,0],"sum_hessian":[1.92744E2,9.131246E1,1.0143154E2],"tree_param":{"num_deleted":"0","num_feature":"156","num_nodes":"3","size_leaf_vector":"1"}},{"base_weights":[-7.169722E-2,-1.2066908E-1,1.2048788E-1],"categories":[],"categories_nodes":[],"categories_segments":[],"categories_sizes":[],"default_left":[0,0,0],"id":10,"left_children":[1,-1,-1],"loss_changes":[2.3797699E2,0E0,0E0],"parents":[2147483647,0,0],"right_children":[2,-1,-1],"split_conditions":[6E0,-1.2066908E-1,1.2048788E-1],"split_indices":[153,0,0],"split_type":[0,0,0],"sum_hessian":[1.6224255E2,8.591286E1,7.63297E1],"tree_param":{"num_deleted":"0","num_feature":"156","num_nodes":"3","size_leaf_vector":"1"}},{"base_weights":[-6.3944824E-2,-1.1806156E-1,1.1789012E-1],"categories":[],"categories_nodes":[],"categories_segments":[],"categories_sizes":[],"default_left":[0,0,0],"id":11,"left_children":[1,-1,-1],"loss_changes":[2.0968803E2,0E0,0E0],"parents":[2147483647,0,0],"right_children":[2,-1,-1],"split_conditions":[6E0,-1.1806156E-1,1.1789012E-1],"split_indices":[153,0,0],"split_type":[0,0,0],"sum_hessian":[1.4908556E2,7.855533E1,7.053022E1],"tree_param":{"num_deleted":"0","num_feature":"156","num_nodes":"3","size_leaf_vector":"1"}},{"base_weights":[8.247456E-2,1.0067326E0,-1.1567847E-1,-9.219026E-2,1.0969505E0,3.8752824E-1,1.1557501E-1,-8.1500046E-2,9.782981E-2],"categories":[],"categories_nodes":[],"categories_segments":[],"categories_sizes":[],"default_left":[0,0,0,0,0,0,0,0,0],"id":12,"left_children":[1,3,-1,-1,5,7,-1,-1,-1],"loss_changes":[1.8425853E2,1.7036057E1,0E0,0E0,3.2412262E0,6.674982E0,0E0,0E0,0E0],"parents":[2147483647,0,0,1,1,4,4,5,5],"right_children":[2,4,-1,-1,6,8,-1,-1,-1],"split_conditions":[3.9726028E0,3.1144824E0,-1.1567847E-1,-9.219026E-2,5.147815E0,1.8769231E0,1.1557501E-1,-8.1500046E-2,9.782981E-2],"split_indices":[142,137,0,0,137,6,0,0,0],"split_type":[0,0,0,0,0,0,0,0,0],"sum_hessian":[1.588522E2,9.109776E1,6.775444E1,3.658992E0,8.7438774E1,7.27354E0,8.016524E1,2.2710986E0,5.0024414E0],"tree_param":{"num_deleted":"0","num_feature":"156","num_nodes":"9","size_leaf_vector":"1"}},{"base_weights":[1.8568158E-2,-1.1383142E-1,1.1386005E-1],"categories":[],"categories_nodes":[],"categories_segments":[],"categories_sizes":[],"default_left":[0,0,0],"id":13,"left_children":[1,-1,-1],"loss_changes":[1.7884628E2,0E0,0E0],"parents":[2147483647,0,0],"right_children":[2,-1,-1],"split_conditions":[6E0,-1.1383142E-1,1.1386005E-1],"split_indices":[153,0,0],"split_type":[0,0,0],"sum_hessian":[1.360255E2,6.6903984E1,6.9121506E1],"tree_param":{"num_deleted":"0","num_feature":"156","num_nodes":"3","size_leaf_vector":"1"}},{"base_weights":[4.4890866E-2,-1.1207082E-1,1.1218121E-1],"categories":[],"categories_nodes":[],"categories_segments":[],"categories_sizes":[],"default_left":[0,0,0],"id":14,"left_children":[1,-1,-1],"loss_changes":[1.6604517E2,0E0,0E0],"parents":[2147483647,0,0],"right_children":[2,-1,-1],"split_conditions":[6E0,-1.1207082E-1,1.1218121E-1],"split_indices":[153,0,0],"split_type":[0,0,0],"sum_hessian":[1.302781E2,6.254368E1,6.773443E1],"tree_param":{"num_deleted":"0","num_feature":"156","num_nodes":"3","size_leaf_vector":"1"}},{"base_weights":[-2.2198757E-2,-1.10442184E-1,1.103242E-1],"categories":[],"categories_nodes":[],"categories_segments":[],"categories_sizes":[],"default_left":[0,0,0],"id":15,"left_children":[1,-1,-1],"loss_changes":[1.3743494E2,0E0,0E0],"parents":[2147483647,0,0],"right_children":[2,-1,-1],"split_conditions":[6E0,-1.10442184E-1,1.103242E-1],"split_indices":[153,0,0],"split_type":[0,0,0],"sum_hessian":[1.1083824E2,5.6513535E1,5.4324703E1],"tree_param":{"num_deleted":"0","num_feature":"156","num_nodes":"3","size_leaf_vector":"1"}},{"base_weights":[-1.0915138E-1,-1.0900592E-1,1.08540766E-1],"categories":[],"categories_nodes":[],"categories_segments":[],"categories_sizes":[],"default_left":[0,0,0],"id":16,"left_children":[1,-1,-1],"loss_changes":[1.1351191E2,0E0,0E0],"parents":[2147483647,0,0],"right_children":[2,-1,-1],"split_conditions":[6E0,-1.0900592E-1,1.08540766E-1],"split_indices":[153,0,0],"split_type":[0,0,0],"sum_hessian":[9.4863914E1,5.2138256E1,4.272566E1],"tree_param":{"num_deleted":"0","num_feature":"156","num_nodes":"3","size_leaf_vector":"1"}},{"base_weights":[5.21779E-2,-1.0767167E-1,1.078695E-1],"categories":[],"categories_nodes":[],"categories_segments":[],"categories_sizes":[],"default_left":[0,0,0],"id":17,"left_children":[1,-1,-1],"loss_changes":[1.1767022E2,0E0,0E0],"parents":[2147483647,0,0],"right_children":[2,-1,-1],"split_conditions":[6E0,-1.0767167E-1,1.078695E-1],"split_indices":[153,0,0],"split_type":[0,0,0],"sum_hessian":[9.954005E1,4.738276E1,5.2157288E1],"tree_param":{"num_deleted":"0","num_feature":"156","num_nodes":"3","size_leaf_vector":"1"}},{"base_weights":[-2.5229083E-2,-1.06501095E-1,1.06374696E-1],"categories":[],"categories_nodes":[],"categories_segments":[],"categories_sizes":[],"default_left":[0,0,0],"id":18,"left_children":[1,-1,-1],"loss_changes":[9.9062126E1,0E0,0E0],"parents":[2147483647,0,0],"right_children":[2,-1,-1],"split_conditions":[6E0,-1.06501095E-1,1.06374696E-1],"split_indices":[153,0,0],"split_type":[0,0,0],"sum_hessian":[8.548718E1,4.3742626E1,4.1744556E1],"tree_param":{"num_deleted":"0","num_feature":"156","num_nodes":"3","size_leaf_vector":"1"}},{"base_weights":[-1.4721802E-2,-1.0534703E-1,1.0526403E-1],"categories":[],"categories_nodes":[],"categories_segments":[],"categories_sizes":[],"default_left":[0,0,0],"id":19,"left_children":[1,-1,-1],"loss_changes":[8.801627E1,0E0,0E0],"parents":[2147483647,0,0],"right_children":[2,-1,-1],"split_conditions":[6E0,-1.0534703E-1,1.0526403E-1],"split_indices":[153,0,0],"split_type":[0,0,0],"sum_hessian":[7.738525E1,3.9224895E1,3.8160347E1],"tree_param":{"num_deleted":"0","num_feature":"156","num_nodes":"3","size_leaf_vector":"1"}},{"base_weights":[-2.2035984E-2,-1.0435974E-1,1.04231216E-1],"categories":[],"categories_nodes":[],"categories_segments":[],"categories_sizes":[],"default_left":[0,0,0],"id":20,"left_children":[1,-1,-1],"loss_changes":[7.959785E1,0E0,0E0],"parents":[2147483647,0,0],"right_children":[2,-1,-1],"split_conditions":[6E0,-1.0435974E-1,1.04231216E-1],"split_indices":[153,0,0],"split_type":[0,0,0],"sum_hessian":[7.120667E1,3.634359E1,3.4863087E1],"tree_param":{"num_deleted":"0","num_feature":"156","num_nodes":"3","size_leaf_vector":"1"}}]},"name":"gbtree"},"learner_model_param":{"base_score":"[5E-1]","boost_from_average":"1","num_class":"0","num_feature":"156","num_target":"1"},"objective":{"name":"binary:logistic","reg_loss_param":{"scale_pos_weight":"39.6470604"}}},"version":[3,2,0]}